{
    "videos": [{
            "id": 1,
            "src": "https://www.youtube.com/embed/APVM2Trt1aw?si=RsWa8VnlKevSFNeF",
            "description": "Quién Soy (Videoclip)"
        },
        {
            "id": 2,
            "src": "https://www.youtube.com/embed/NbI-mWFenIE?si=TqJ49xjSZkttWzLa",
            "description": "Una Noche Rara (Videoclip)"
        },
        {
            "id": 3,
            "src": "https://www.youtube.com/embed/IYb2QIvx29c?si=2EEJCJ68EHpZBLFi",
            "description": "OLAS - Estela Julia Quartet 2022"
        },
        {
            "id": 4,
            "src": "https://www.youtube.com/embed/DAh-QiTJoY8?si=KeyeGcPse63tVaeU",
            "description": "ORBEA (live)"
        }
    ]
}